korg/__init__.py
korg/_julia_import.py
korg/_python_interface.py
korg/_version.py
korg/juliapkg.json
korg/py.typed
korg/unstable.py
korg-0.0.1.dist-info/METADATA
korg-0.0.1.dist-info/WHEEL
korg-0.0.1.dist-info/licenses/LICENSE
korg-0.0.1.dist-info/RECORD
